neocitizen/__init__.py
neocitizen/api.py
neocitizen/cli.py
neocitizen/errors.py
neocitizen/index.html
neocitizen/types.py
neocitizen/utils.py
neocitizen-1.0.0.dist-info/entry_points.txt
neocitizen-1.0.0.dist-info/LICENSE
neocitizen-1.0.0.dist-info/WHEEL
neocitizen-1.0.0.dist-info/METADATA
neocitizen-1.0.0.dist-info/RECORD
